<annotation>
	<folder>JPEGImages</folder>
	<filename>people(3493).jpg</filename>
	<path>D:\ipynb_files\神经网络\FallDown\JPEGImages\people(3493).jpg</path>
	<source>
		<database>Unknown</database>
	</source>
	<size>
		<width>232</width>
		<height>282</height>
		<depth>3</depth>
	</size>
	<segmented>0</segmented>
	<object>
		<name>down</name>
		<pose>Unspecified</pose>
		<truncated>0</truncated>
		<difficult>0</difficult>
		<bndbox>
			<xmin>66</xmin>
			<ymin>173</ymin>
			<xmax>231</xmax>
			<ymax>245</ymax>
		</bndbox>
	</object>
	<object>
		<name>bending</name>
		<pose>Unspecified</pose>
		<truncated>0</truncated>
		<difficult>0</difficult>
		<bndbox>
			<xmin>86</xmin>
			<ymin>106</ymin>
			<xmax>152</xmax>
			<ymax>228</ymax>
		</bndbox>
	</object>
	<object>
		<name>up</name>
		<pose>Unspecified</pose>
		<truncated>0</truncated>
		<difficult>0</difficult>
		<bndbox>
			<xmin>122</xmin>
			<ymin>54</ymin>
			<xmax>158</xmax>
			<ymax>156</ymax>
		</bndbox>
	</object>
	<object>
		<name>up</name>
		<pose>Unspecified</pose>
		<truncated>1</truncated>
		<difficult>0</difficult>
		<bndbox>
			<xmin>205</xmin>
			<ymin>52</ymin>
			<xmax>232</xmax>
			<ymax>184</ymax>
		</bndbox>
	</object>
	<object>
		<name>up</name>
		<pose>Unspecified</pose>
		<truncated>0</truncated>
		<difficult>0</difficult>
		<bndbox>
			<xmin>88</xmin>
			<ymin>60</ymin>
			<xmax>118</xmax>
			<ymax>160</ymax>
		</bndbox>
	</object>
	<object>
		<name>up</name>
		<pose>Unspecified</pose>
		<truncated>0</truncated>
		<difficult>0</difficult>
		<bndbox>
			<xmin>44</xmin>
			<ymin>60</ymin>
			<xmax>76</xmax>
			<ymax>152</ymax>
		</bndbox>
	</object>
	<object>
		<name>up</name>
		<pose>Unspecified</pose>
		<truncated>1</truncated>
		<difficult>0</difficult>
		<bndbox>
			<xmin>1</xmin>
			<ymin>50</ymin>
			<xmax>38</xmax>
			<ymax>155</ymax>
		</bndbox>
	</object>
	<object>
		<name>up</name>
		<pose>Unspecified</pose>
		<truncated>0</truncated>
		<difficult>0</difficult>
		<bndbox>
			<xmin>70</xmin>
			<ymin>70</ymin>
			<xmax>90</xmax>
			<ymax>137</ymax>
		</bndbox>
	</object>
	<object>
		<name>up</name>
		<pose>Unspecified</pose>
		<truncated>0</truncated>
		<difficult>0</difficult>
		<bndbox>
			<xmin>150</xmin>
			<ymin>69</ymin>
			<xmax>174</xmax>
			<ymax>151</ymax>
		</bndbox>
	</object>
</annotation>
