<annotation>
	<folder>image</folder>
	<filename>people(1779).jpg</filename>
	<path>D:\pycharm_project\pythonProject7\fall\image\people(1779).jpg</path>
	<source>
		<database>Unknown</database>
	</source>
	<size>
		<width>576</width>
		<height>450</height>
		<depth>3</depth>
	</size>
	<segmented>0</segmented>
	<object>
		<name>bending</name>
		<pose>Unspecified</pose>
		<truncated>0</truncated>
		<difficult>0</difficult>
		<bndbox>
			<xmin>9</xmin>
			<ymin>57</ymin>
			<xmax>167</xmax>
			<ymax>419</ymax>
		</bndbox>
	</object>
	<object>
		<name>down</name>
		<pose>Unspecified</pose>
		<truncated>0</truncated>
		<difficult>0</difficult>
		<bndbox>
			<xmin>188</xmin>
			<ymin>274</ymin>
			<xmax>466</xmax>
			<ymax>420</ymax>
		</bndbox>
	</object>
	<object>
		<name>up</name>
		<pose>Unspecified</pose>
		<truncated>0</truncated>
		<difficult>0</difficult>
		<bndbox>
			<xmin>119</xmin>
			<ymin>14</ymin>
			<xmax>253</xmax>
			<ymax>432</ymax>
		</bndbox>
	</object>
	<object>
		<name>bending</name>
		<pose>Unspecified</pose>
		<truncated>0</truncated>
		<difficult>0</difficult>
		<bndbox>
			<xmin>262</xmin>
			<ymin>60</ymin>
			<xmax>375</xmax>
			<ymax>362</ymax>
		</bndbox>
	</object>
	<object>
		<name>up</name>
		<pose>Unspecified</pose>
		<truncated>0</truncated>
		<difficult>0</difficult>
		<bndbox>
			<xmin>409</xmin>
			<ymin>6</ymin>
			<xmax>557</xmax>
			<ymax>428</ymax>
		</bndbox>
	</object>
</annotation>
