<annotation>
	<folder>JPEGImages</folder>
	<filename>people(5068).jpg</filename>
	<path>D:\ipynb_files\神经网络\FallDown\JPEGImages\people(5068).jpg</path>
	<source>
		<database>Unknown</database>
	</source>
	<size>
		<width>433</width>
		<height>391</height>
		<depth>3</depth>
	</size>
	<segmented>0</segmented>
	<object>
		<name>down</name>
		<pose>Unspecified</pose>
		<truncated>0</truncated>
		<difficult>0</difficult>
		<bndbox>
			<xmin>160</xmin>
			<ymin>88</ymin>
			<xmax>337</xmax>
			<ymax>240</ymax>
		</bndbox>
	</object>
	<object>
		<name>bending</name>
		<pose>Unspecified</pose>
		<truncated>0</truncated>
		<difficult>0</difficult>
		<bndbox>
			<xmin>271</xmin>
			<ymin>17</ymin>
			<xmax>419</xmax>
			<ymax>216</ymax>
		</bndbox>
	</object>
	<object>
		<name>bending</name>
		<pose>Unspecified</pose>
		<truncated>0</truncated>
		<difficult>0</difficult>
		<bndbox>
			<xmin>76</xmin>
			<ymin>32</ymin>
			<xmax>225</xmax>
			<ymax>239</ymax>
		</bndbox>
	</object>
</annotation>
