<annotation>
	<folder>JPEGImages</folder>
	<filename>people(2398).jpg</filename>
	<path>D:\ipynb_files\神经网络\FallDown\JPEGImages\people(2398).jpg</path>
	<source>
		<database>Unknown</database>
	</source>
	<size>
		<width>800</width>
		<height>532</height>
		<depth>3</depth>
	</size>
	<segmented>0</segmented>
	<object>
		<name>bending</name>
		<pose>Unspecified</pose>
		<truncated>0</truncated>
		<difficult>0</difficult>
		<bndbox>
			<xmin>111</xmin>
			<ymin>223</ymin>
			<xmax>230</xmax>
			<ymax>324</ymax>
		</bndbox>
	</object>
	<object>
		<name>bending</name>
		<pose>Unspecified</pose>
		<truncated>0</truncated>
		<difficult>0</difficult>
		<bndbox>
			<xmin>226</xmin>
			<ymin>201</ymin>
			<xmax>307</xmax>
			<ymax>314</ymax>
		</bndbox>
	</object>
	<object>
		<name>up</name>
		<pose>Unspecified</pose>
		<truncated>0</truncated>
		<difficult>0</difficult>
		<bndbox>
			<xmin>627</xmin>
			<ymin>153</ymin>
			<xmax>685</xmax>
			<ymax>347</ymax>
		</bndbox>
	</object>
	<object>
		<name>bending</name>
		<pose>Unspecified</pose>
		<truncated>0</truncated>
		<difficult>0</difficult>
		<bndbox>
			<xmin>317</xmin>
			<ymin>210</ymin>
			<xmax>386</xmax>
			<ymax>305</ymax>
		</bndbox>
	</object>
	<object>
		<name>bending</name>
		<pose>Unspecified</pose>
		<truncated>0</truncated>
		<difficult>0</difficult>
		<bndbox>
			<xmin>387</xmin>
			<ymin>182</ymin>
			<xmax>485</xmax>
			<ymax>329</ymax>
		</bndbox>
	</object>
	<object>
		<name>up</name>
		<pose>Unspecified</pose>
		<truncated>0</truncated>
		<difficult>0</difficult>
		<bndbox>
			<xmin>596</xmin>
			<ymin>133</ymin>
			<xmax>657</xmax>
			<ymax>271</ymax>
		</bndbox>
	</object>
	<object>
		<name>up</name>
		<pose>Unspecified</pose>
		<truncated>0</truncated>
		<difficult>0</difficult>
		<bndbox>
			<xmin>668</xmin>
			<ymin>104</ymin>
			<xmax>695</xmax>
			<ymax>178</ymax>
		</bndbox>
	</object>
	<object>
		<name>up</name>
		<pose>Unspecified</pose>
		<truncated>0</truncated>
		<difficult>0</difficult>
		<bndbox>
			<xmin>703</xmin>
			<ymin>108</ymin>
			<xmax>719</xmax>
			<ymax>155</ymax>
		</bndbox>
	</object>
	<object>
		<name>up</name>
		<pose>Unspecified</pose>
		<truncated>0</truncated>
		<difficult>0</difficult>
		<bndbox>
			<xmin>691</xmin>
			<ymin>113</ymin>
			<xmax>711</xmax>
			<ymax>161</ymax>
		</bndbox>
	</object>
	<object>
		<name>up</name>
		<pose>Unspecified</pose>
		<truncated>0</truncated>
		<difficult>0</difficult>
		<bndbox>
			<xmin>730</xmin>
			<ymin>111</ymin>
			<xmax>754</xmax>
			<ymax>160</ymax>
		</bndbox>
	</object>
	<object>
		<name>up</name>
		<pose>Unspecified</pose>
		<truncated>0</truncated>
		<difficult>0</difficult>
		<bndbox>
			<xmin>713</xmin>
			<ymin>108</ymin>
			<xmax>737</xmax>
			<ymax>161</ymax>
		</bndbox>
	</object>
	<object>
		<name>up</name>
		<pose>Unspecified</pose>
		<truncated>0</truncated>
		<difficult>0</difficult>
		<bndbox>
			<xmin>754</xmin>
			<ymin>105</ymin>
			<xmax>778</xmax>
			<ymax>163</ymax>
		</bndbox>
	</object>
	<object>
		<name>up</name>
		<pose>Unspecified</pose>
		<truncated>1</truncated>
		<difficult>0</difficult>
		<bndbox>
			<xmin>780</xmin>
			<ymin>117</ymin>
			<xmax>800</xmax>
			<ymax>190</ymax>
		</bndbox>
	</object>
</annotation>
